{
    "name": "IL PORCOSPINO ALLE CAPPELLE MEDICEE",
    "description": "",
    "address": "11, Piazza Di Madonna Degli Aldobrandini - 50123 Firenze (FI)",
    "streetAddress": "11, Piazza Di Madonna Degli Aldobrandini",
    "postalCode": "50123",
    "addressLocality": "Firenze",
    "addressRegion": "(FI)",
    "coordinates": {
        "lat": 43.77495,
        "lon": 11.2528
    },
    "categories": [
        "Ristoranti"
    ],
    "telephone": [
        "055 392946",
        "055 217700"
    ],
    "rating": "4.5"
}