{
    "name": "LO CHALET SNC DI FRAGORZI ANGELA E GIARDINI GIOVANNI",
    "description": "",
    "address": "69, Via Forlivese - 50060 San Godenzo (FI)",
    "streetAddress": "69, Via Forlivese",
    "postalCode": "50060",
    "addressLocality": "San Godenzo",
    "addressRegion": "(FI)",
    "coordinates": {
        "lat": 43.92834,
        "lon": 11.62104
    },
    "categories": [
        "Pizzerie"
    ],
    "telephone": [
        "333 9606335",
        "055 8374043"
    ],
    "rating": ""
}